backgrounds/__init__.py
backgrounds/analysis.py
backgrounds/core.py
backgrounds/expectations.py
backgrounds/fisher.py
backgrounds/instru.py
backgrounds/loadings.py
backgrounds/noise.py
backgrounds/plotting.py
backgrounds/priors.py
backgrounds/psd.py
backgrounds/sampling.py
backgrounds/signal.py
backgrounds/tdi.py
backgrounds/utils.py
backgrounds-0.1.3.dist-info/LICENSE
backgrounds-0.1.3.dist-info/METADATA
backgrounds-0.1.3.dist-info/WHEEL
backgrounds-0.1.3.dist-info/RECORD
