Metadata-Version: 2.3
Name: backgrounds
Version: 0.1.3
Summary: A set of tools for LISA stochastic gravitational wave detection
License: BSD-3-Clause
Author: Quentin Baghi
Author-email: quentin.baghi@protonmail.com
Requires-Python: >=3.11,<4.0
Classifier: License :: OSI Approved :: BSD License
Classifier: Programming Language :: Python :: 3
Classifier: Programming Language :: Python :: 3.11
Classifier: Programming Language :: Python :: 3.12
Classifier: Programming Language :: Python :: 3.13
Requires-Dist: h5py (>=3.14.0,<4.0.0)
Requires-Dist: interpax (>=0.3.12,<0.4.0)
Requires-Dist: ipykernel (>=6.29.5,<7.0.0)
Requires-Dist: jax (>=0.6.2,<0.7.0)
Requires-Dist: lisaconstants (>=1.3.6,<2.0.0)
Requires-Dist: lisagwresponse (>=2.5.0,<3.0.0)
Requires-Dist: lisaorbits (>=2.4.2,<3.0.0)
Requires-Dist: matplotlib (>=3.10.3,<4.0.0)
Requires-Dist: numpy (>=2.3.1,<3.0.0)
Requires-Dist: ptemcee (>=1.0.0,<2.0.0)
Requires-Dist: pytest (>=8.4.1,<9.0.0)
Requires-Dist: scipy (>=1.16.0,<2.0.0)
Requires-Dist: segwo (>=1.0.0,<2.0.0)
